Workbook

Sheet ALL
A1: Office | B1: Issue Date | C1: Type | D1: Document Number | E1: Title | F1: Total Page Count (inclusive of Attachments) | G1: Determination | H1: Reason for Determination | I1: Name of Person Making Determination | J1: Email of Person Making Determination | K1: Program | M1: URL
A2: CB | B2: 28921 | C2: Action Transmittal (AT) | D2: AT-79-12 | F2: 35
A3: CB | B3: 29277 | C3: Action Transmittal (AT) | D3: AT-80-01 | F3: 4
A4: CB | B4: 29315 | C4: Action Transmittal (AT) | D4: AT-80-02 | F4: 1
A5: CB | B5: 29332 | C5: Action Transmittal (AT) | D5: AT-80-03 | F5: 5
A6: CB | B6: 29389 | C6: Action Transmittal (AT) | D6: AT-80-04 | F6: 10
A7: CB | B7: 29454 | C7: Action Transmittal (AT) | D7: AT-80-05 | F7: 4
A8: CB | B8: 29508 | C8: Action Transmittal (AT) | D8: AT-81-01 | F8: 1 | L8: Link to AT seems missing; Print to PDF used for count
A9: CB | B9: 29508 | C9: Program Instruction (PI) | D9: PI-80-01 | F9: 1
A10: CB | B10: 29521 | C10: Program Instruction (PI) | D10: PI-80-02 | F10: 1
A11: CB | B11: 29574 | C11: Program Instruction (PI) | D11: PI-80-03 | F11: 2
A12: CB | B12: 29588 | C12: Information Memorandum (IM) | D12: IM-81-01 | F12: 2
A13: CB | B13: 29593 | C13: Program Instruction (PI) | D13: PI-81-01 | F13: 2
A14: CB | B14: 29664 | C14: Information Memorandum (IM) | D14: IM-81-02 | F14: 5
A15: CB | B15: 29668 | C15: Program Instruction (PI) | D15: PI-81-02 | F15: 3
A16: CB | B16: 29706 | C16: Information Memorandum (IM) | D16: IM-81-03 | F16: 2
A17: CB | B17: 29711 | C17: Program Instruction (PI) | D17: PI-81-06 | F17: 4
A18: CB | B18: 29746 | C18: Action Transmittal (AT) | D18: AT-81-16 | F18: 4
A19: CB | B19: 29746 | C19: Program Instruction (PI) | D19: PI-81-05 | F19: 10
A20: CB | B20: 29768 | C20: Program Instruction (PI) | D20: PI-81-07 | F20: 5
... A104: CB | B104: 32988 | C104: Information Memorandum (IM) | D104: IM-90-17 | F104: 7
A105: CB | B105: 33024 | C105: Information Memorandum (IM) | D105: IM-90-11 | F105: 7 | L105: Comes up when you search PI but not IM
A106: CB | B106: 33053 | C106: Information Memorandum (IM) | D106: IM-90-18 | F106: 11
A107: CB | B107: 33148 | C107: Program Instruction (PI) | D107: PI-90-16 | F107: 13
A108: CB | B108: 33219 | C108: Information Memorandum (IM) | D108: IM-90-26 | F108: 4
A109: CB | B109: 33221 | C109: Information Memorandum (IM) | D109: IM-90-27 | F109: 5
A110: CB | B110: 33221 | C110: Information Memorandum (IM) | D110: IM-90-28 | F110: 8
A111: CB | B111: 33368 | C111: Information Memorandum (IM) | D111: IM-91-11 | F111: 2
A112: CB | B112: 33443 | C112: Information Memorandum (IM) | D112: IM-91-15 | F112: 2
A113: CB | B113: 33485 | C113: Information Memorandum (IM) | D113: IM-91-19 | F113: 1
A114: CB | B114: 33571 | C114: Information Memorandum (IM) | D114: IM-91-25 | F114: 11
A115: CB | B115: 33584 | C115: Action Transmittal (AT) | D115: AT-91-33 | F115: 2
A116: CB | B116: 33619 | C116: Action Transmittal (AT) | D116: AT-92-05 | F116: 4
A117: CB | B117: 33658 | C117: Information Memorandum (IM) | D117: IM-92-04 | F117: 2
... A195: CB | B195: 35975 | C195: Program Instruction (PI) | D195: PI-98-10 | F195: 2
A196: CB | B196: 35982 | C196: Program Instruction (PI) | D196: PI-98-11 | E196: Adoption and Foster Care Analysis and Reporting System Penalties | F196: 6
A197: CB | B197: 35991 | C197: Program Instruction (PI) | D197: PI-98-12 | F197: 3
A198: CB | B198: 35999 | C198: Program Instruction (PI) | D198: PI-98-13 | F198: 18
A199: CB | B199: 36027 | C199: Program Instruction (PI) | D199: PI-98-14 | F199: 4
A200: CB | B200: 36028 | C200: Action Transmittal (AT) | D200: AT-98-05 | F200: 25
A201: CB | B201: 36057 | C201: Program Instruction (PI) | D201: PI-98-15 | F201: 31
A202: CB | B202: 36063 | C202: Information Memorandum (IM) | D202: IM-98-04 | F202: 5
A203: CB | B203: 36083 | C203: Information Memorandum (IM) | D203: IM-98-05 | F203: 3
A204: CB | B204: 36166 | C204: Information Memorandum (IM) | D204: IM-99-01 | F204: 10
A205: CB | B205: 36171 | C205: Information Memorandum (IM) | D205: IM-99-02 | F205: 29
A206: CB | B206: 36181 | C206: Information Memorandum (IM) | D206: IM-99-03 | F206: 41
A207: CB | B207: 36187 | C207: Program Instruction (PI) | D207: PI-99-01 | F207: 29
A208: CB | B208: 36214 | C208: Program Instruction (PI) | D208: PI-99-02 | F208: 24
... A215: CB | B215: 36574 | C215: Information Memorandum (IM) | D215: IM-00-02 | F215: 7
A216: CB | B216: 36598 | C216: Action Transmittal (AT) | D216: AT-OSSP-00-01 | E216: FEDERAL/STATE INFORMATION TECHNOLOGY POLICY— Department of Health and Human Services Approval of Funding, When a State Fails to Obtain Prior Written Approval In Accordance with 45 CFR Part 95, Subpart F | F216: 6
A217: CB | B217: 36601 | C217: Information Memorandum (IM) | D217: IM-00-03 | F217: 7
A218: CB | B218: 36615 | C218: Information Memorandum (IM) | D218: IM-00-04 | F218: 4
A219: CB | B219: 36634 | C219: Program Instruction (PI) | D219: PI-00-03 | F219: 82
A220: CB | B220: 36636 | C220: Information Memorandum (IM) | D220: IM-00-07 | F220: 3
A221: CB | B221: 36636 | C221: Program Instruction (PI) | D221: PI-00-04 | F221: 19
A222: CB | B222: 36690 | C222: Information Memorandum (IM) | D222: IM-00-09 | F222: 15
A223: CB | B223: 36888 | C223: Information Memorandum (IM) | D223: IM-00-11 | F223: 8
A224: CB | B224: 36934 | C224: Program Instruction (PI) | D224: PI-01-02 | F224: 35
A225: CB | B225: 36936 | C225: Program Instruction (PI) | D225: PI-01-03 | F225: 101
A226: CB | B226: 36943 | C226: Information Memorandum (IM) | D226: IM-01-01 | F226: 6
A227: CB | B227: 36957 | C227: Information Memorandum (IM) | D227: IM-01-03 | F227: 2
A228: CB | B228: 36997 | C228: Program Instruction (PI) | D228: PI-01-05 | F228: 12
A229: CB | B229: 37008 | C229: Program Instruction (PI) | D229: PI-01-06 | F229: 96
A230: CB | B230: 37012 | C230: Policy Guide (PG) | E230: Child Welfare Policy Manual | F230: 469
A231: CB | B231: 37015 | C231: Program Instruction (PI) | D231: PI-01-07 | F231: 6
A232: CB | B232: 37055 | C232: Information Memorandum (IM) | D232: IM-01-04 | F232: 4
A233: CB | B233: 37075 | C233: Information Memorandum (IM) | D233: IM-01-05 | F233: 3
A234: CB | B234: 37075 | C234: Information Memorandum (IM) | D234: IM-01-06 | F234: 5
A235: CB | B235: 37119 | C235: Information Memorandum (IM) | D235: IM-01-07 | F235: 5
A236: CB | B236: 37125 | C236: Program Instruction (PI) | D236: PI-01-08 | F236: 16
A237: CB | B237: 37189 | C237: Information Memorandum (IM) | D237: IM-01-09 | F237: 4
A238: CB | B238: 37201 | C238: Information Memorandum (IM) | D238: IM-01-08 | F238: 4
A239: CB | B239: 37202 | C239: Program Instruction (PI) | D239: PI-01-09 | F239: 2
A240: CB | B240: 37221 | C240: Information Memorandum (IM) | D240: IM-01-10 | F240: 2
A241: CB | B241: 37225 | C241: Information Memorandum (IM) | D241: IM-01-11 | F241: 69
A242: CB | B242: 37312 | C242: Program Instruction (PI) | D242: PI-02-01 | F242: 21
... A250: CB | B250: 37386 | C250: Program Instruction (PI) | D250: PI-02-05 | F250: 62
A251: CB | B251: 37399 | C251: Information Memorandum (IM) | D251: IM-02-06 | E251: Title IV-E Child Welfare Demonstration Projects Requests for Extensions – Procedures and Criteria | F251: 5
A252: CB | B252: 37405 | C252: Information Memorandum (IM) | D252: IM-02-07 | F252: 1
A253: CB | B253: 37449 | C253: Program Instruction (PI) | D253: PI-02-06 | F253: 2
A254: CB | B254: 37487 | C254: Program Instruction (PI) | D254: PI-02-07 | F254: 17
A255: CB | B255: 37531 | C255: Program Instruction (PI) | D255: PI-02-08 | F255: 2
A256: CB | B256: 37536 | C256: Program Instruction (PI) | D256: PI-02-09 | F256: 5
A257: CB | B257: 37694 | C257: Program Instruction (PI) | D257: PI-03-03 | F257: 37
A258: CB | B258: 37705 | C258: Information Memorandum (IM) | D258: IM-03-01 | F258: 3
A259: CB | B259: 37708 | C259: Program Instruction (PI) | D259: PI-03-04 | F259: 41
A260: CB | B260: 37720 | C260: Program Instruction (PI) | D260: PI-03-01 | F260: 58
A261: CB | B261: 37736 | C261: Program Instruction (PI) | D261: PI-03-02 | F261: 17
A262: CB | B262: 37749 | C262: Information Memorandum (IM) | D262: IM-03-02 | F262: 2
A263: CB | B263: 37764 | C263: Program Instruction (PI) | D263: PI-03-05 | F263: 35
... A282: CB | B282: 38194 | C282: Information Memorandum (IM) | D282: IM-04-08 | F282: 3
A283: CB | B283: 38383 | C283: Technical Bulletin (TB) / Frequently Asked Questions (FAQ) | D283: Child and Family Services Review Technical Bulletin #1 | E283: Child and Family Services Review Technical Bulletin #1 | F283: 9
A284: CB | B284: 38385 | C284: Information Memorandum (IM) | D284: IM-05-01 | F284: 4
A285: CB | B285: 38457 | C285: Program Instruction (PI) | D285: PI-05-03 | F285: 54
A286: CB | B286: 38464 | C286: Program Instruction (PI) | D286: PI-05-01 | F286: 3
A287: CB | B287: 38471 | C287: Program Instruction (PI) | D287: PI-05-05 | F287: 32
A288: CB | B288: 38471 | C288: Program Instruction (PI) | D288: PI-05-04 | F288: 51
A289: CB | B289: 38474 | C289: Information Memorandum (IM) | D289: ACF-CMS-FNS IM 05-04 | F289: 5
A290: CB | B290: 38475 | C290: Information Memorandum (IM) | D290: IM-05-02 | F290: 5
A291: CB | B291: 38475 | C291: Information Memorandum (IM) | D291: IM-05-04 | F291: 3
...

Sheet Total Counts
A1: Type | D1: CB | E1: CB # | F1: OCC | G1: OCC # | H1: OCSE | I1: OCSE # | J1: ORR | K1: ORR # | L1: OCS | M1: OCS # | N1: ECD | O1: ECD # | P1: ANA | Q1: ANA # | R1: OFVPS | S1: OFVPS # | T1: OTIP | U1: OTIP # | V1: OHSEPR | W1: OHSEPR # | X1: FYSB | Y1: FYSB # | Z1: OFA | AA1: OFA # | AB1: OHS | AC1: OHS #
A2: Action Transmittal (AT) | D2: x | E2: =COUNTIFS(ALL!$C:$C,$A2,ALL!$A:$A,D$1) -> 17 | F2: n/a | G2: =COUNTIFS(ALL!$C:$C,$A2,ALL!$A:$A,F$1) -> 0 | H2: x | I2: =COUNTIFS(ALL!$C:$C,$A2,ALL!$A:$A,H$1) -> 319 | J2: n/a | K2: =COUNTIFS(ALL!$C:$C,$A2,ALL!$A:$A,J$1) -> 0 | L2: x | M2: =COUNTIFS(ALL!$C:$C,$A2,ALL!$A:$A,L$1) -> 97 | N2: n/a | O2: =COUNTIFS(ALL!$C:$C,$A2,ALL!$A:$A,N$1) -> 0 | P2: n/a | Q2: =COUNTIFS(ALL!$C:$C,$A2,ALL!$A:$A,P$1) -> 0 | R2: n/a | S2: =COUNTIFS(ALL!$C:$C,$A2,ALL!$A:$A,R$1) -> 0 | T2: n/a | U2: =COUNTIFS(ALL!$C:$C,$A2,ALL!$A:$A,T$1) -> 0 | V2: x | W2: =COUNTIFS(ALL!$C:$C,$A2,ALL!$A:$A,V$1) -> 5 | X2: n/a | Y2: =COUNTIFS(ALL!$C:$C,$A2,ALL!$A:$A,X$1) -> 0 | Z2: n/a | AA2: =COUNTIFS(ALL!$C:$C,$A2,ALL!$A:$A,Z$1) -> 0 | AB2: n/a | AC2: =COUNTIFS(ALL!$C:$C,$A2,ALL!$A:$A,AB$1) -> 0
A3: Dear Colleague Letter (DCL) | D3: x | E3: =COUNTIFS(ALL!$C:$C,$A3,ALL!$A:$A,D$1) -> 24 | F3: x | G3: =COUNTIFS(ALL!$C:$C,$A3,ALL!$A:$A,F$1) -> 4 | H3: x | I3: =COUNTIFS(ALL!$C:$C,$A3,ALL!$A:$A,H$1) -> 192 | J3: x | K3: =COUNTIFS(ALL!$C:$C,$A3,ALL!$A:$A,J$1) -> 156 | L3: x | M3: =COUNTIFS(ALL!$C:$C,$A3,ALL!$A:$A,L$1) -> 161 | N3: x | O3: =COUNTIFS(ALL!$C:$C,$A3,ALL!$A:$A,N$1) -> 5 | P3: x | Q3: =COUNTIFS(ALL!$C:$C,$A3,ALL!$A:$A,P$1) -> 1 | R3: n/a | S3: =COUNTIFS(ALL!$C:$C,$A3,ALL!$A:$A,R$1) -> 0 | T3: x | U3: =COUNTIFS(ALL!$C:$C,$A3,ALL!$A:$A,T$1) -> 1 | V3: x | W3: =COUNTIFS(ALL!$C:$C,$A3,ALL!$A:$A,V$1) -> 2 | X3: n/a | Y3: =COUNTIFS(ALL!$C:$C,$A3,ALL!$A:$A,X$1) -> 0 | Z3: x | AA3: =COUNTIFS(ALL!$C:$C,$A3,ALL!$A:$A,Z$1) -> 29 | AB3: x | AC3: =COUNTIFS(ALL!$C:$C,$A3,ALL!$A:$A,AB$1) -> 4
A4: Field Guidance (FG) | D4: x | E4: =COUNTIFS(ALL!$C:$C,$A4,ALL!$A:$A,D$1) -> 28 | F4: n/a | G4: =COUNTIFS(ALL!$C:$C,$A4,ALL!$A:$A,F$1) -> 0 | H4: x | I4: =COUNTIFS(ALL!$C:$C,$A4,ALL!$A:$A,H$1) -> 49 | J4: x | K4: =COUNTIFS(ALL!$C:$C,$A4,ALL!$A:$A,J$1) -> 27 | L4: x | M4: =COUNTIFS(ALL!$C:$C,$A4,ALL!$A:$A,L$1) -> 2 | N4: n/a | O4: =COUNTIFS(ALL!$C:$C,$A4,ALL!$A:$A,N$1) -> 0 | P4: n/a | Q4: =COUNTIFS(ALL!$C:$C,$A4,ALL!$A:$A,P$1) -> 0 | R4: x | S4: =COUNTIFS(ALL!$C:$C,$A4,ALL!$A:$A,R$1) -> 1 | T4: x | U4: =COUNTIFS(ALL!$C:$C,$A4,ALL!$A:$A,T$1) -> 7 | V4: n/a | W4: =COUNTIFS(ALL!$C:$C,$A4,ALL!$A:$A,V$1) -> 0 | X4: x | Y4: =COUNTIFS(ALL!$C:$C,$A4,ALL!$A:$A,X$1) -> 2 | Z4: n/a | AA4: =COUNTIFS(ALL!$C:$C,$A4,ALL!$A:$A,Z$1) -> 0 | AB4: x | AC4: =COUNTIFS(ALL!$C:$C,$A4,ALL!$A:$A,AB$1) -> 1
A5: Information Memorandum (IM) | D5: x | E5: =COUNTIFS(ALL!$C:$C,$A5,ALL!$A:$A,D$1) -> 258 | F5: x | G5: =COUNTIFS(ALL!$C:$C,$A5,ALL!$A:$A,F$1) -> 44 | H5: x | I5: =COUNTIFS(ALL!$C:$C,$A5,ALL!$A:$A,H$1) -> 101 | J5: n/a | K5: =COUNTIFS(ALL!$C:$C,$A5,ALL!$A:$A,J$1) -> 1 | L5: x | M5: =COUNTIFS(ALL!$C:$C,$A5,ALL!$A:$A,L$1) -> 103 | N5: x | O5: =COUNTIFS(ALL!$C:$C,$A5,ALL!$A:$A,N$1) -> 2 | P5: n/a | Q5: =COUNTIFS(ALL!$C:$C,$A5,ALL!$A:$A,P$1) -> 0 | R5: x | S5: =COUNTIFS(ALL!$C:$C,$A5,ALL!$A:$A,R$1) -> 3 | T5: x | U5: =COUNTIFS(ALL!$C:$C,$A5,ALL!$A:$A,T$1) -> 5 | V5: x | W5: =COUNTIFS(ALL!$C:$C,$A5,ALL!$A:$A,V$1) -> 3 | X5: n/a | Y5: =COUNTIFS(ALL!$C:$C,$A5,ALL!$A:$A,X$1) -> 0 | Z5: x | AA5: =COUNTIFS(ALL!$C:$C,$A5,ALL!$A:$A,Z$1) -> 79 | AB5: x | AC5: =COUNTIFS(ALL!$C:$C,$A5,ALL!$A:$A,AB$1) -> 38
A6: Policy Interpretation Question (PIQ) | D6: n/a | E6: =COUNTIFS(ALL!$C:$C,$A6,ALL!$A:$A,D$1) -> 0 | F6: x | G6: =COUNTIFS(ALL!$C:$C,$A6,ALL!$A:$A,F$1) -> 10 | H6: x | I6: =COUNTIFS(ALL!$C:$C,$A6,ALL!$A:$A,H$1) -> 60 | J6: n/a | K6: =COUNTIFS(ALL!$C:$C,$A6,ALL!$A:$A,J$1) -> 0 | L6: n/a | M6: =COUNTIFS(ALL!$C:$C,$A6,ALL!$A:$A,L$1) -> 0 | N6: n/a | O6: =COUNTIFS(ALL!$C:$C,$A6,ALL!$A:$A,N$1) -> 0 | P6: n/a | Q6: =COUNTIFS(ALL!$C:$C,$A6,ALL!$A:$A,P$1) -> 0 | R6: n/a | S6: =COUNTIFS(ALL!$C:$C,$A6,ALL!$A:$A,R$1) -> 0 | T6: n/a | U6: =COUNTIFS(ALL!$C:$C,$A6,ALL!$A:$A,T$1) -> 0 | V6: n/a | W6: =COUNTIFS(ALL!$C:$C,$A6,ALL!$A:$A,V$1) -> 0 | X6: n/a | Y6: =COUNTIFS(ALL!$C:$C,$A6,ALL!$A:$A,X$1) -> 0 | Z6: n/a | AA6: =COUNTIFS(ALL!$C:$C,$A6,ALL!$A:$A,Z$1) -> 0 | AB6: n/a | AC6: =COUNTIFS(ALL!$C:$C,$A6,ALL!$A:$A,AB$1) -> 0
A7: Policy Guide (PG) | D7: x | E7: =COUNTIFS(ALL!$C:$C,$A7,ALL!$A:$A,D$1) -> 1 | F7: x | G7: =COUNTIFS(ALL!$C:$C,$A7,ALL!$A:$A,F$1) -> 1 | H7: n/a | I7: =COUNTIFS(ALL!$C:$C,$A7,ALL!$A:$A,H$1) -> 0 | J7: x | K7: =COUNTIFS(ALL!$C:$C,$A7,ALL!$A:$A,J$1) -> 2 | L7: x | M7: =COUNTIFS(ALL!$C:$C,$A7,ALL!$A:$A,L$1) -> 1 | N7: x | O7: =COUNTIFS(ALL!$C:$C,$A7,ALL!$A:$A,N$1) -> 1 | P7: x | Q7: =COUNTIFS(ALL!$C:$C,$A7,ALL!$A:$A,P$1) -> 1 | R7: n/a | S7: =COUNTIFS(ALL!$C:$C,$A7,ALL!$A:$A,R$1) -> 0 | T7: x | U7: =COUNTIFS(ALL!$C:$C,$A7,ALL!$A:$A,T$1) -> 1 | V7: x | W7: =COUNTIFS(ALL!$C:$C,$A7,ALL!$A:$A,V$1) -> 7 | X7: n/a | Y7: =COUNTIFS(ALL!$C:$C,$A7,ALL!$A:$A,X$1) -> 0 | Z7: x | AA7: =COUNTIFS(ALL!$C:$C,$A7,ALL!$A:$A,Z$1) -> 1 | AB7: n/a | AC7: =COUNTIFS(ALL!$C:$C,$A7,ALL!$A:$A,AB$1) -> 0
A8: Policy Letter (PL) | D8: x | E8: =COUNTIFS(ALL!$C:$C,$A8,ALL!$A:$A,D$1) -> 1 | F8: n/a | G8: =COUNTIFS(ALL!$C:$C,$A8,ALL!$A:$A,F$1) -> 0 | H8: n/a | I8: =COUNTIFS(ALL!$C:$C,$A8,ALL!$A:$A,H$1) -> 0 | J8: x | K8: =COUNTIFS(ALL!$C:$C,$A8,ALL!$A:$A,J$1) -> 315 | L8: n/a | M8: =COUNTIFS(ALL!$C:$C,$A8,ALL!$A:$A,L$1) -> 0 | N8: n/a | O8: =COUNTIFS(ALL!$C:$C,$A8,ALL!$A:$A,N$1) -> 0 | P8: n/a | Q8: =COUNTIFS(ALL!$C:$C,$A8,ALL!$A:$A,P$1) -> 0 | R8: n/a | S8: =COUNTIFS(ALL!$C:$C,$A8,ALL!$A:$A,R$1) -> 0 | T8: n/a | U8: =COUNTIFS(ALL!$C:$C,$A8,ALL!$A:$A,T$1) -> 0 | V8: n/a | W8: =COUNTIFS(ALL!$C:$C,$A8,ALL!$A:$A,V$1) -> 0 | X8: x | Y8: =COUNTIFS(ALL!$C:$C,$A8,ALL!$A:$A,X$1) -> 1 | Z8: x | AA8: =COUNTIFS(ALL!$C:$C,$A8,ALL!$A:$A,Z$1) -> 16 | AB8: n/a | AC8: =COUNTIFS(ALL!$C:$C,$A8,ALL!$A:$A,AB$1) -> 0
A9: Program Instruction (PI) | D9: x | E9: =COUNTIFS(ALL!$C:$C,$A9,ALL!$A:$A,D$1) -> 297 | F9: x | G9: =COUNTIFS(ALL!$C:$C,$A9,ALL!$A:$A,F$1) -> 134 | H9: n/a | I9: =COUNTIFS(ALL!$C:$C,$A9,ALL!$A:$A,H$1) -> 0 | J9: n/a | K9: =COUNTIFS(ALL!$C:$C,$A9,ALL!$A:$A,J$1) -> 0 | L9: x | M9: =COUNTIFS(ALL!$C:$C,$A9,ALL!$A:$A,L$1) -> 1 | N9: n/a | O9: =COUNTIFS(ALL!$C:$C,$A9,ALL!$A:$A,N$1) -> 0 | P9: n/a | Q9: =COUNTIFS(ALL!$C:$C,$A9,ALL!$A:$A,P$1) -> 0 | R9: n/a | S9: =COUNTIFS(ALL!$C:$C,$A9,ALL!$A:$A,R$1) -> 0 | T9: x | U9: =COUNTIFS(ALL!$C:$C,$A9,ALL!$A:$A,T$1) -> 4 | V9: n/a | W9: =COUNTIFS(ALL!$C:$C,$A9,ALL!$A:$A,V$1) -> 0 | X9: n/a | Y9: =COUNTIFS(ALL!$C:$C,$A9,ALL!$A:$A,X$1) -> 0 | Z9: x | AA9: =COUNTIFS(ALL!$C:$C,$A9,ALL!$A:$A,Z$1) -> 153 | AB9: x | AC9: =COUNTIFS(ALL!$C:$C,$A9,ALL!$A:$A,AB$1) -> 41
A10: Technical Bulletin (TB) / Frequently Asked Questions (FAQ) | D10: x | E10: =COUNTIFS(ALL!$C:$C,$A10,ALL!$A:$A,D$1) -> 103 | F10: x | G10: =COUNTIFS(ALL!$C:$C,$A10,ALL!$A:$A,F$1) -> 100 | H10: x | I10: =COUNTIFS(ALL!$C:$C,$A10,ALL!$A:$A,H$1) -> 45 | J10: x | K10: =COUNTIFS(ALL!$C:$C,$A10,ALL!$A:$A,J$1) -> 3 | L10: x | M10: =COUNTIFS(ALL!$C:$C,$A10,ALL!$A:$A,L$1) -> 5 | N10: n/a | O10: =COUNTIFS(ALL!$C:$C,$A10,ALL!$A:$A,N$1) -> 0 | P10: n/a | Q10: =COUNTIFS(ALL!$C:$C,$A10,ALL!$A:$A,P$1) -> 0 | R10: x | S10: =COUNTIFS(ALL!$C:$C,$A10,ALL!$A:$A,R$1) -> 8 | T10: n/a | U10: =COUNTIFS(ALL!$C:$C,$A10,ALL!$A:$A,T$1) -> 0 | V10: x | W10: =COUNTIFS(ALL!$C:$C,$A10,ALL!$A:$A,V$1) -> 2 | X10: x | Y10: =COUNTIFS(ALL!$C:$C,$A10,ALL!$A:$A,X$1) -> 12 | Z10: x | AA10: =COUNTIFS(ALL!$C:$C,$A10,ALL!$A:$A,Z$1) -> 51 | AB10: x | AC10: =COUNTIFS(ALL!$C:$C,$A10,ALL!$A:$A,AB$1) -> 30
A11: Other | D11: x | E11: =COUNTIFS(ALL!$C:$C,$A11,ALL!$A:$A,D$1) -> 33 | F11: x | G11: =COUNTIFS(ALL!$C:$C,$A11,ALL!$A:$A,F$1) -> 21 | H11: x | I11: =COUNTIFS(ALL!$C:$C,$A11,ALL!$A:$A,H$1) -> 1 | J11: x | K11: =COUNTIFS(ALL!$C:$C,$A11,ALL!$A:$A,J$1) -> 40 | L11: x | M11: =COUNTIFS(ALL!$C:$C,$A11,ALL!$A:$A,L$1) -> 13 | N11: x | O11: =COUNTIFS(ALL!$C:$C,$A11,ALL!$A:$A,N$1) -> 37 | P11: n/a | Q11: =COUNTIFS(ALL!$C:$C,$A11,ALL!$A:$A,P$1) -> 0 | R11: x | S11: =COUNTIFS(ALL!$C:$C,$A11,ALL!$A:$A,R$1) -> 4 | T11: n/a | U11: =COUNTIFS(ALL!$C:$C,$A11,ALL!$A:$A,T$1) -> 0 | V11: x | W11: =COUNTIFS(ALL!$C:$C,$A11,ALL!$A:$A,V$1) -> 1 | X11: x | Y11: =COUNTIFS(ALL!$C:$C,$A11,ALL!$A:$A,X$1) -> 7 | Z11: x | AA11: =COUNTIFS(ALL!$C:$C,$A11,ALL!$A:$A,Z$1) -> 19 | AB11: x | AC11: =COUNTIFS(ALL!$C:$C,$A11,ALL!$A:$A,AB$1) -> 28
C12: Total document count | E12: =SUM(E2:E11) -> 762 | G12: =SUM(G2:G11) -> 314 | I12: =SUM(I2:I11) -> 767 | K12: =SUM(K2:K11) -> 544 | M12: =SUM(M2:M11) -> 383 | O12: =SUM(O2:O11) -> 45 | Q12: =SUM(Q2:Q11) -> 2 | S12: =SUM(S2:S11) -> 16 | U12: =SUM(U2:U11) -> 18 | W12: =SUM(W2:W11) -> 20 | Y12: =SUM(Y2:Y11) -> 22 | AA12: =SUM(AA2:AA11) -> 348 | AC12: =SUM(AC2:AC11) -> 142
C13: Total Page Count | D13: =SUM(ALL!F:F) -> 48408

Sheet Data Validation
A1: Determination | B1: Type
A2: Confirmed Necessary | B2: Action Transmittal (AT)
A3: Confirmed Obsolete | B3: Dear Colleague Letter (DCL)
B4: Field Guidance (FG)
B5: Information Memorandum (IM)
B6: Policy Interpretation Question (PIQ)
B7: Policy Guide (PG)
B8: Policy Letter (PL)
B9: Program Instruction (PI)
B10: Technical Bulletin (TB) / Frequently Asked Questions (FAQ)
B11: Other
